{"children":[{"text":"安肃镇","value":"130609100"},{"text":"崔庄镇","value":"130609101"},{"text":"大因镇","value":"130609102"},{"text":"遂城镇","value":"130609103"},{"text":"高林村镇","value":"130609104"},{"text":"大王店镇","value":"130609105"},{"text":"漕河镇","value":"130609106"},{"text":"东史端乡","value":"130609200"},{"text":"留村乡","value":"130609201"},{"text":"正村乡","value":"130609202"},{"text":"户木乡","value":"130609203"},{"text":"瀑河乡","value":"130609204"},{"text":"东釜山乡","value":"130609205"},{"text":"义联庄乡","value":"130609206"}],"value":"130609"}