{"children":[{"text":"湓城街道","value":"360481001"},{"text":"桂林街道","value":"360481002"},{"text":"码头镇","value":"360481100"},{"text":"白杨镇","value":"360481101"},{"text":"南义镇","value":"360481102"},{"text":"横港镇","value":"360481103"},{"text":"范镇","value":"360481104"},{"text":"肇陈镇","value":"360481105"},{"text":"高丰镇","value":"360481106"},{"text":"夏畈镇","value":"360481107"},{"text":"乐园乡","value":"360481200"},{"text":"洪一乡","value":"360481201"},{"text":"花园乡","value":"360481202"},{"text":"洪下乡","value":"360481203"},{"text":"武蛟乡","value":"360481204"},{"text":"横立山乡","value":"360481205"},{"text":"黄金乡","value":"360481206"},{"text":"南阳乡","value":"360481207"}],"value":"360481"}