{"children":[{"text":"舞泉镇","value":"411121100"},{"text":"吴城镇","value":"411121101"},{"text":"北舞渡镇","value":"411121102"},{"text":"莲花镇","value":"411121103"},{"text":"辛安镇","value":"411121104"},{"text":"孟寨镇","value":"411121105"},{"text":"太尉镇","value":"411121106"},{"text":"侯集镇","value":"411121107"},{"text":"九街镇","value":"411121108"},{"text":"文峰乡","value":"411121200"},{"text":"保和乡","value":"411121201"},{"text":"马村乡","value":"411121202"},{"text":"姜店乡","value":"411121204"},{"text":"章化乡","value":"411121206"}],"value":"411121"}