{"children":[{"text":"容城镇","value":"421023100"},{"text":"朱河镇","value":"421023101"},{"text":"新沟镇","value":"421023102"},{"text":"龚场镇","value":"421023103"},{"text":"周老嘴镇","value":"421023104"},{"text":"黄歇口镇","value":"421023105"},{"text":"汪桥镇","value":"421023106"},{"text":"程集镇","value":"421023107"},{"text":"分盐镇","value":"421023108"},{"text":"毛市镇","value":"421023109"},{"text":"福田寺镇","value":"421023110"},{"text":"上车湾镇","value":"421023111"},{"text":"汴河镇","value":"421023112"},{"text":"尺八镇","value":"421023113"},{"text":"白螺镇","value":"421023114"},{"text":"网市镇","value":"421023115"},{"text":"三洲镇","value":"421023116"},{"text":"桥市镇","value":"421023117"},{"text":"红城乡","value":"421023200"},{"text":"棋盘乡","value":"421023201"},{"text":"柘木乡","value":"421023202"}],"value":"421023"}