{"children":[{"text":"桃洪镇","value":"430524100"},{"text":"小沙江镇","value":"430524101"},{"text":"金石桥镇","value":"430524102"},{"text":"司门前镇","value":"430524103"},{"text":"高平镇","value":"430524104"},{"text":"六都寨镇","value":"430524105"},{"text":"荷香桥镇","value":"430524106"},{"text":"横板桥镇","value":"430524107"},{"text":"周旺镇","value":"430524108"},{"text":"滩头镇","value":"430524109"},{"text":"鸭田镇","value":"430524110"},{"text":"西洋江镇","value":"430524111"},{"text":"雨山铺镇","value":"430524112"},{"text":"岩口镇","value":"430524113"},{"text":"北山镇","value":"430524114"},{"text":"三阁司镇","value":"430524115"},{"text":"南岳庙镇","value":"430524116"},{"text":"七江镇","value":"430524117"},{"text":"麻塘山乡","value":"430524200"},{"text":"虎形山瑶族乡","value":"430524201"},{"text":"大水田乡","value":"430524203"},{"text":"羊古坳乡","value":"430524204"},{"text":"罗洪乡","value":"430524205"},{"text":"荷田乡","value":"430524207"},{"text":"石门乡","value":"430524208"},{"text":"山界回族乡","value":"430524212"}],"value":"430524"}