{"children":[{"text":"沱江镇","value":"431129100"},{"text":"桥头铺镇","value":"431129101"},{"text":"东田镇","value":"431129102"},{"text":"大路铺镇","value":"431129103"},{"text":"白芒营镇","value":"431129104"},{"text":"涛圩镇","value":"431129105"},{"text":"河路口镇","value":"431129106"},{"text":"小圩镇","value":"431129107"},{"text":"大圩镇","value":"431129108"},{"text":"水口镇","value":"431129109"},{"text":"码市镇","value":"431129110"},{"text":"界牌乡","value":"431129200"},{"text":"桥市乡","value":"431129201"},{"text":"大石桥乡","value":"431129202"},{"text":"清塘壮族乡","value":"431129203"},{"text":"两岔河乡","value":"431129204"},{"text":"务江乡","value":"431129205"},{"text":"花江乡","value":"431129206"},{"text":"湘江乡","value":"431129207"},{"text":"贝江乡","value":"431129208"},{"text":"未竹口乡","value":"431129209"},{"text":"大锡乡","value":"431129210"}],"value":"431129"}