{"children":[{"text":"芷江镇","value":"431228100"},{"text":"罗旧镇","value":"431228101"},{"text":"新店坪镇","value":"431228102"},{"text":"碧涌镇","value":"431228103"},{"text":"公坪镇","value":"431228104"},{"text":"牛牯坪乡","value":"431228201"},{"text":"艾头坪乡","value":"431228202"},{"text":"岩桥乡","value":"431228203"},{"text":"水宽乡","value":"431228204"},{"text":"木叶溪乡","value":"431228206"},{"text":"五郎溪乡","value":"431228207"},{"text":"麻缨塘乡","value":"431228208"},{"text":"竹坪铺乡","value":"431228209"},{"text":"土桥乡","value":"431228210"},{"text":"上坪乡","value":"431228211"},{"text":"大树坳乡","value":"431228212"},{"text":"大洪山乡","value":"431228213"},{"text":"杨公庙乡","value":"431228214"},{"text":"梨溪口乡","value":"431228215"},{"text":"洞下场乡","value":"431228216"},{"text":"罗岩乡","value":"431228217"},{"text":"板山乡","value":"431228218"},{"text":"大垅乡","value":"431228219"},{"text":"禾梨坳乡","value":"431228220"},{"text":"冷水溪乡","value":"431228221"},{"text":"楠木坪乡","value":"431228222"},{"text":"晓坪乡","value":"431228223"},{"text":"罗卜田乡","value":"431228224"}],"value":"431228"}