{"children":[{"text":"古巷镇","value":"445103100"},{"text":"登塘镇","value":"445103101"},{"text":"凤塘镇","value":"445103103"},{"text":"浮洋镇","value":"445103104"},{"text":"龙湖镇","value":"445103105"},{"text":"金石镇","value":"445103106"},{"text":"沙溪镇","value":"445103107"},{"text":"彩塘镇","value":"445103108"},{"text":"东凤镇","value":"445103109"},{"text":"庵埠镇","value":"445103110"},{"text":"江东镇","value":"445103114"},{"text":"归湖镇","value":"445103115"},{"text":"文祠镇","value":"445103116"},{"text":"凤凰镇","value":"445103117"},{"text":"赤凤镇","value":"445103120"},{"text":"枫溪镇","value":"445103121"}],"value":"445103"}