{"children":[{"text":"竹阳街道","value":"511724001"},{"text":"东柳街道","value":"511724002"},{"text":"白塔街道","value":"511724003"},{"text":"乌木镇","value":"511724101"},{"text":"团坝镇","value":"511724102"},{"text":"杨家镇","value":"511724103"},{"text":"清河镇","value":"511724104"},{"text":"柏林镇","value":"511724105"},{"text":"石河镇","value":"511724106"},{"text":"双拱镇","value":"511724107"},{"text":"石桥铺镇","value":"511724108"},{"text":"观音镇","value":"511724109"},{"text":"周家镇","value":"511724110"},{"text":"石子镇","value":"511724111"},{"text":"文星镇","value":"511724112"},{"text":"妈妈镇","value":"511724113"},{"text":"高穴镇","value":"511724114"},{"text":"欧家镇","value":"511724115"},{"text":"庙坝镇","value":"511724116"},{"text":"清水镇","value":"511724117"},{"text":"月华镇","value":"511724118"},{"text":"高明镇","value":"511724119"},{"text":"童家镇","value":"511724120"},{"text":"天城镇","value":"511724121"},{"text":"城西乡","value":"511724200"},{"text":"竹北乡","value":"511724201"},{"text":"朝阳乡","value":"511724203"},{"text":"人和乡","value":"511724204"},{"text":"中华乡","value":"511724205"},{"text":"黄家乡","value":"511724206"},{"text":"柏家乡","value":"511724207"},{"text":"李家乡","value":"511724208"},{"text":"二郎乡","value":"511724210"},{"text":"蒲包乡","value":"511724211"},{"text":"永胜乡","value":"511724212"},{"text":"新生乡","value":"511724213"},{"text":"安吉乡","value":"511724214"},{"text":"白坝乡","value":"511724215"},{"text":"双溪乡","value":"511724216"},{"text":"八渡乡","value":"511724218"},{"text":"中和乡","value":"511724219"},{"text":"杨通乡","value":"511724220"},{"text":"四合乡","value":"511724222"},{"text":"张家乡","value":"511724223"},{"text":"神合乡","value":"511724225"},{"text":"金鸡乡","value":"511724226"},{"text":"黄滩乡","value":"511724227"},{"text":"牌坊乡","value":"511724228"},{"text":"姚市乡","value":"511724229"},{"text":"莲印乡","value":"511724230"},{"text":"川主乡","value":"511724231"}],"value":"511724"}