{"children":[{"text":"城厢镇","value":"511825100"},{"text":"始阳镇","value":"511825101"},{"text":"小河乡","value":"511825200"},{"text":"思经乡","value":"511825201"},{"text":"鱼泉乡","value":"511825202"},{"text":"紫石乡","value":"511825203"},{"text":"两路乡","value":"511825204"},{"text":"大坪乡","value":"511825205"},{"text":"乐英乡","value":"511825206"},{"text":"多功乡","value":"511825207"},{"text":"仁义乡","value":"511825208"},{"text":"老场乡","value":"511825209"},{"text":"新华乡","value":"511825210"},{"text":"新场乡","value":"511825211"},{"text":"兴业乡","value":"511825212"}],"value":"511825"}