{"children":[{"text":"诺江镇","value":"511921100"},{"text":"民胜镇","value":"511921101"},{"text":"火炬镇","value":"511921102"},{"text":"广纳镇","value":"511921103"},{"text":"铁佛镇","value":"511921104"},{"text":"麻石镇","value":"511921105"},{"text":"至诚镇","value":"511921106"},{"text":"洪口镇","value":"511921107"},{"text":"沙溪镇","value":"511921108"},{"text":"瓦室镇","value":"511921109"},{"text":"永安镇","value":"511921110"},{"text":"铁溪镇","value":"511921111"},{"text":"涪阳镇","value":"511921112"},{"text":"诺水河镇","value":"511921113"},{"text":"杨柏乡","value":"511921200"},{"text":"大兴乡","value":"511921201"},{"text":"东山乡","value":"511921202"},{"text":"三溪乡","value":"511921203"},{"text":"双泉乡","value":"511921204"},{"text":"文峰乡","value":"511921205"},{"text":"春在乡","value":"511921206"},{"text":"三合乡","value":"511921207"},{"text":"云昙乡","value":"511921208"},{"text":"唱歌乡","value":"511921209"},{"text":"芝苞乡","value":"511921210"},{"text":"龙凤场乡","value":"511921211"},{"text":"董溪乡","value":"511921212"},{"text":"澌波乡","value":"511921213"},{"text":"松溪乡","value":"511921214"},{"text":"九层乡","value":"511921215"},{"text":"胜利乡","value":"511921216"},{"text":"板凳乡","value":"511921217"},{"text":"文胜乡","value":"511921218"},{"text":"兴隆乡","value":"511921219"},{"text":"毛裕乡","value":"511921220"},{"text":"泥溪乡","value":"511921221"},{"text":"烟溪乡","value":"511921222"},{"text":"沙坪乡","value":"511921223"},{"text":"朱元乡","value":"511921224"},{"text":"长坪乡","value":"511921225"},{"text":"两河口乡","value":"511921226"},{"text":"空山乡","value":"511921227"},{"text":"青浴乡","value":"511921228"},{"text":"板桥口乡","value":"511921229"},{"text":"铁厂乡","value":"511921230"},{"text":"新场乡","value":"511921231"},{"text":"陈河乡","value":"511921232"},{"text":"草池乡","value":"511921233"},{"text":"回林乡","value":"511921234"}],"value":"511921"}