{"children":[{"text":"岳阳镇","value":"512021100"},{"text":"鸳大镇","value":"512021101"},{"text":"石桥铺镇","value":"512021102"},{"text":"通贤镇","value":"512021103"},{"text":"龙台镇","value":"512021104"},{"text":"姚市镇","value":"512021105"},{"text":"林凤镇","value":"512021106"},{"text":"毛家镇","value":"512021107"},{"text":"永清镇","value":"512021108"},{"text":"永顺镇","value":"512021109"},{"text":"石羊镇","value":"512021110"},{"text":"两板桥镇","value":"512021111"},{"text":"护龙镇","value":"512021112"},{"text":"李家镇","value":"512021113"},{"text":"元坝镇","value":"512021114"},{"text":"兴隆镇","value":"512021115"},{"text":"天林镇","value":"512021116"},{"text":"镇子镇","value":"512021117"},{"text":"文化镇","value":"512021118"},{"text":"周礼镇","value":"512021119"},{"text":"驯龙镇","value":"512021120"},{"text":"华严镇","value":"512021121"},{"text":"卧佛镇","value":"512021122"},{"text":"长河源镇","value":"512021123"},{"text":"忠义镇","value":"512021124"},{"text":"护建镇","value":"512021125"},{"text":"南薰镇","value":"512021126"},{"text":"城北乡","value":"512021200"},{"text":"城西乡","value":"512021201"},{"text":"思贤乡","value":"512021202"},{"text":"石鼓乡","value":"512021203"},{"text":"来凤乡","value":"512021205"},{"text":"天马乡","value":"512021206"},{"text":"人和乡","value":"512021207"},{"text":"团结乡","value":"512021209"},{"text":"悦来乡","value":"512021210"},{"text":"白水乡","value":"512021211"},{"text":"云峰乡","value":"512021212"},{"text":"岳新乡","value":"512021213"},{"text":"偏岩乡","value":"512021214"},{"text":"东胜乡","value":"512021215"},{"text":"坪河乡","value":"512021216"},{"text":"乾龙乡","value":"512021217"},{"text":"高升乡","value":"512021218"},{"text":"横庙乡","value":"512021219"},{"text":"瑞云乡","value":"512021220"},{"text":"白塔寺乡","value":"512021221"},{"text":"双龙街乡","value":"512021222"},{"text":"顶新乡","value":"512021223"},{"text":"和平乡","value":"512021224"},{"text":"高屋乡","value":"512021225"},{"text":"合义乡","value":"512021227"},{"text":"努力乡","value":"512021228"},{"text":"清流乡","value":"512021230"},{"text":"共和乡","value":"512021231"},{"text":"天宝乡","value":"512021232"},{"text":"协和乡","value":"512021233"},{"text":"鱼龙乡","value":"512021234"},{"text":"建华乡","value":"512021235"},{"text":"大平乡","value":"512021236"},{"text":"九龙乡","value":"512021237"},{"text":"岳源乡","value":"512021238"},{"text":"龙桥乡","value":"512021239"},{"text":"千佛乡","value":"512021240"},{"text":"拱桥乡","value":"512021241"},{"text":"宝华乡","value":"512021242"},{"text":"自治乡","value":"512021244"},{"text":"大埝乡","value":"512021245"},{"text":"朝阳乡","value":"512021246"}],"value":"512021"}