{"children":[{"text":"城关街道","value":"610523001"},{"text":"许庄镇","value":"610523101"},{"text":"朝邑镇","value":"610523102"},{"text":"安仁镇","value":"610523103"},{"text":"两宜镇","value":"610523104"},{"text":"羌白镇","value":"610523105"},{"text":"官池镇","value":"610523106"},{"text":"冯村镇","value":"610523107"},{"text":"双泉镇","value":"610523108"},{"text":"下寨镇","value":"610523110"},{"text":"韦林镇","value":"610523111"},{"text":"范家镇","value":"610523112"},{"text":"苏村镇","value":"610523113"},{"text":"赵渡镇","value":"610523114"},{"text":"埝桥镇","value":"610523116"},{"text":"段家镇","value":"610523117"}],"value":"610523"}