{"children":[{"text":"街道","value":"620822001"},{"text":"中台镇","value":"620822100"},{"text":"邵寨镇","value":"620822101"},{"text":"独店镇","value":"620822102"},{"text":"什字镇","value":"620822103"},{"text":"朝那镇","value":"620822104"},{"text":"西屯镇","value":"620822105"},{"text":"上良镇","value":"620822106"},{"text":"新开乡","value":"620822201"},{"text":"梁原乡","value":"620822204"},{"text":"龙门乡","value":"620822205"},{"text":"星火乡","value":"620822206"},{"text":"百里乡","value":"620822207"},{"text":"蒲窝乡","value":"620822208"}],"value":"620822"}