{"children":[{"text":"察布查尔镇","value":"654022100"},{"text":"爱新色里镇","value":"654022101"},{"text":"孙扎齐牛录镇","value":"654022102"},{"text":"堆齐牛录乡","value":"654022200"},{"text":"绰霍尔乡","value":"654022202"},{"text":"纳达齐牛录乡","value":"654022203"},{"text":"扎库齐牛录乡","value":"654022204"},{"text":"米粮泉回族乡","value":"654022205"},{"text":"坎乡","value":"654022206"},{"text":"阔洪奇乡","value":"654022207"},{"text":"海努克乡","value":"654022208"},{"text":"加尕斯台乡","value":"654022209"},{"text":"琼博拉乡","value":"654022210"}],"value":"654022"}