<?xml version="1.0" encoding="UTF-8" ?>
<!DOCTYPE mapper PUBLIC "-//mybatis.org//DTD Mapper 3.0//EN" "http://mybatis.org/dtd/mybatis-3-mapper.dtd" >
<mapper namespace="com.codi.laolaiqiao.domain.UserImage" >
  <resultMap id="BaseResultMap" type="com.codi.laolaiqiao.domain.UserImage" >
    <!--
      WARNING - @mbggenerated
      This element is automatically generated by MyBatis Generator, do not modify.
      This element was generated on Thu Dec 29 20:49:16 CST 2016.
    -->
    <id column="open_id" property="openId" jdbcType="VARCHAR" />
    <result column="image_url" property="imageUrl" jdbcType="VARCHAR" />
  </resultMap>
  <sql id="Base_Column_List" >
    <!--
      WARNING - @mbggenerated
      This element is automatically generated by MyBatis Generator, do not modify.
      This element was generated on Thu Dec 29 20:49:16 CST 2016.
    -->
    open_id, image_url
  </sql>
  <select id="selectByPrimaryKey" resultMap="BaseResultMap" parameterType="java.lang.String" >
    <!--
      WARNING - @mbggenerated
      This element is automatically generated by MyBatis Generator, do not modify.
      This element was generated on Thu Dec 29 20:49:16 CST 2016.
    -->
    select 
    <include refid="Base_Column_List" />
    from user_image
    where open_id = #{openId,jdbcType=VARCHAR}
  </select>
  <delete id="deleteByPrimaryKey" parameterType="java.lang.String" >
    <!--
      WARNING - @mbggenerated
      This element is automatically generated by MyBatis Generator, do not modify.
      This element was generated on Thu Dec 29 20:49:16 CST 2016.
    -->
    delete from user_image
    where open_id = #{openId,jdbcType=VARCHAR}
  </delete>
  <insert id="insert" parameterType="com.codi.laolaiqiao.domain.UserImage" >
    <!--
      WARNING - @mbggenerated
      This element is automatically generated by MyBatis Generator, do not modify.
      This element was generated on Thu Dec 29 20:49:16 CST 2016.
    -->
    insert into user_image (open_id, image_url)
    values (#{openId,jdbcType=VARCHAR}, #{imageUrl,jdbcType=VARCHAR})
  </insert>
  <insert id="insertSelective" parameterType="com.codi.laolaiqiao.domain.UserImage" >
    <!--
      WARNING - @mbggenerated
      This element is automatically generated by MyBatis Generator, do not modify.
      This element was generated on Thu Dec 29 20:49:16 CST 2016.
    -->
    insert into user_image
    <trim prefix="(" suffix=")" suffixOverrides="," >
      <if test="openId != null" >
        open_id,
      </if>
      <if test="imageUrl != null" >
        image_url,
      </if>
    </trim>
    <trim prefix="values (" suffix=")" suffixOverrides="," >
      <if test="openId != null" >
        #{openId,jdbcType=VARCHAR},
      </if>
      <if test="imageUrl != null" >
        #{imageUrl,jdbcType=VARCHAR},
      </if>
    </trim>
  </insert>
  <update id="updateByPrimaryKeySelective" parameterType="com.codi.laolaiqiao.domain.UserImage" >
    <!--
      WARNING - @mbggenerated
      This element is automatically generated by MyBatis Generator, do not modify.
      This element was generated on Thu Dec 29 20:49:16 CST 2016.
    -->
    update user_image
    <set >
      <if test="imageUrl != null" >
        image_url = #{imageUrl,jdbcType=VARCHAR},
      </if>
    </set>
    where open_id = #{openId,jdbcType=VARCHAR}
  </update>
  <update id="updateByPrimaryKey" parameterType="com.codi.laolaiqiao.domain.UserImage" >
    <!--
      WARNING - @mbggenerated
      This element is automatically generated by MyBatis Generator, do not modify.
      This element was generated on Thu Dec 29 20:49:16 CST 2016.
    -->
    update user_image
    set image_url = #{imageUrl,jdbcType=VARCHAR}
    where open_id = #{openId,jdbcType=VARCHAR}
  </update>
</mapper>